pfms/__init__.py
pfms/flask_pf_marshmallow_swagger.py
pfms/common/__init__.py
pfms/common/common_processor.py
pfms/common/enum_processor.py
pfms/common/pfms_data_type.py
pfms/common/pfms_exception.py
pfms/common/pfms_util.py
pfms/example/__init__.py
pfms/example/api_v1_user.py
pfms/example/dto/__init__.py
pfms/example/dto/details.py
pfms/pf-marshmallow-swagger/css/swagger-ui.css
pfms/pf-marshmallow-swagger/js/swagger-ui-bundle.js
pfms/pf-marshmallow-swagger/js/swagger-ui-standalone-preset.js
pfms/pfapi/__init__.py
pfms/pfapi/pfms_cons.py
pfms/pfapi/base/__init__.py
pfms/pfapi/base/pfms_base_schema.py
pfms/pfapi/rr/__init__.py
pfms/pfapi/rr/api_request.py
pfms/pfapi/rr/api_response.py
pfms/pfapi/rr/base_response.py
pfms/pfapi/rr/data_response.py
pfms/pfapi/rr/pfms_request_processor.py
pfms/pfapi/rr/pfms_request_respons.py
pfms/pfapi/rr/pfms_response_processor.py
pfms/swagger/__init__.py
pfms/swagger/pfms_actions_to_definition.py
pfms/swagger/pfms_definition.py
pfms/swagger/pfms_definition_to_swagger.py
pfms/swagger/pfms_swagger_api_spec.py
pfms/swagger/pfms_swagger_cons.py
pfms/swagger/pfms_swagger_decorator.py
pfms/swagger/pfms_swagger_schemas.py
pfms/templates/pf-swagger-ui.html
flask_pf_marshmallow_swagger-1.7.dist-info/LICENSE
flask_pf_marshmallow_swagger-1.7.dist-info/METADATA
flask_pf_marshmallow_swagger-1.7.dist-info/WHEEL
flask_pf_marshmallow_swagger-1.7.dist-info/top_level.txt
flask_pf_marshmallow_swagger-1.7.dist-info/RECORD
