Metadata-Version: 2.1
Name: flask-pf-marshmallow-swagger
Version: 1.7
Summary: This is Problem Fighter Flask Marshmallow Swagger Extension
Home-page: https://github.com/problemfighter/flask-pf-marshmallow-swagger
Author: Touhid Mia
Author-email: hmtm.cse@gmail.com
License: Apache 2.0
Platform: any
Classifier: Environment :: Web Environment
Classifier: Intended Audience :: Developers
Classifier: License :: OSI Approved :: Apache Software License
Classifier: Operating System :: OS Independent
Classifier: Programming Language :: Python
Classifier: Topic :: Internet :: WWW/HTTP :: Dynamic Content
Classifier: Topic :: Software Development :: Libraries :: Python Modules
Requires-Dist: Flask
Requires-Dist: Marshmallow
Requires-Dist: Apispec
Requires-Dist: marshmallow-sqlalchemy
